Workbook

Sheet Name
B7: Name | C7: Pannaga A Kumar
B8: Course | C8: Corporate Valuation and Restructuring
B11: Company Taken | C11: Sun Pharmaceutical Industries Ltd.
B12: Company Stage | C12: Growth Company
B13: Model Followed | C13: 3 Stage Model
B15: Websites Used | C15: Screener.in
C16: Moneycontrol
C17: Focusguru
C18: NSE
B20: No. of Sheets | C20: 7 sheets (Base year & 10 year data; Calculation of Beta; High Growth Phase; Transition Phase; Stable Growth Phase; Calculation of Cost of Equity, WACC, PV of FCFF, TV, and PV of TV; Value of Firm)

Sheet Base year & 10 Year data
B3: 42339 | C3: 42705 | D3: 43070 | E3: 43435 | F3: 43800 | G3: 44166 | H3: 44531 | I3: 44896 | J3: 44986 | K3: March 2024 (Base Year)
A5: Revenues | B5: 27392 | C5: 28487 | D5: 31578 | E5: 26489 | F5: 29066 | G5: 32838 | H5: 33498 | I5: 38654 | J5: 43886 | K5: 48497
A6: EBIT | B6: 7894 | C6: 8174 | D6: 10102 | E6: 5631 | F6: 6377 | G6: 6983 | H6: 8470 | I6: 10258 | J6: 11650 | K6: 13018
A7: Capital Expenditure | B7: -2350 | C7: -3404 | D7: -3693 | E7: -1961 | F7: -3213 | G7: -1542 | H7: -1170 | I7: -1495 | J7: -2086 | K7: -2202
A8: Depreciation | B8: 1195 | C8: 1038 | D8: 1265 | E8: 1500 | F8: 1753 | G8: 2053 | H8: 2080 | I8: 2144 | J8: 2529 | K8: 2557
A9: Net Working Capital | B9: =B26-B23 -> 10240 | C9: =C26-C23 -> 15280 | D9: =D26-D23 -> 17772 | E9: =E26-E23 -> 12319 | F9: =F26-F23 -> 11670 | G9: =G26-G23 -> 12274 | H9: =H26-H23 -> 15297 | I9: =I26-I23 -> 12498 | ... K9: =K26-K23 -> 25430
A10: Corporate Tax Rate | B10: 0.14 | C10: 0.14 | D10: 0.13 | E10: 0.26 | F10: 0.16 | G10: 0.16 | H10: 0.18 | I10: 0.24 | J10: 0.09 | K10: 0.13
A11: Paid Up Equity Capital | B11: 207 | C11: 241 | D11: 240 | E11: 240 | F11: 240 | G11: 240 | H11: 240 | I11: 240 | J11: 240 | K11: 240
A13: Operating Profit Margin (%) | B13: 0.29 | C13: 0.29 | D13: 0.32 | E13: 0.21 | F13: 0.22 | G13: 0.21 | H13: 0.25 | I13: 0.27 | J13: 0.27 | K13: 0.27
A14: NWC as % of Revenues | B14: =B9/B5 -> 0.37383178 | C14: =C9/C5 -> 0.53638502 | D14: =D9/D5 -> 0.56279688 | E14: =E9/E5 -> 0.46506097 | F14: =F9/F5 -> 0.40150003 | G14: =G9/G5 -> 0.37377429 | H14: =H9/H5 -> 0.45665413 | I14: =I9/I5 -> 0.32333006 | ... K14: =K9/K5 -> 0.52436233
A20: Calculation of Net Working Capital
A21: Borrowings | B21: 8996 | C21: 8497 | D21: 9832 | E21: 10385 | F21: 10514 | G21: 8315 | H21: 3869 | I21: 1290 | J21: 6886 | K21: 3274
A22: Other Liabilities | B22: 14089 | C22: 13948 | D22: 14624 | E22: 15598 | F22: 12666 | G22: 14615 | H22: 17291 | I22: 20474 | J22: 17831 | K22: 18367
A23: Current Liabilities | B23: =B21+B22 -> 23085 | C23: =C21+C22 -> 22445 | D23: =D21+D22 -> 24456 | E23: =E21+E22 -> 25983 | F23: =F21+F22 -> 23180 | G23: =G21+G22 -> 22930 | H23: =H21+H22 -> 21160 | I23: =I21+I22 -> 21764 | ... K23: =K21+K22 -> 21641
A24: CWIP | B24: 2039 | C24: 2175 | D24: 2801 | E24: 2465 | F24: 1411 | G24: 1220 | H24: 1567 | I24: 1287 | J24: 4973 | K24: 5354
A25: Other Assets | B25: 31286 | C25: 35550 | D25: 39427 | E25: 35837 | F25: 33439 | G25: 33984 | H25: 34890 | I25: 32975 | J25: 36849 | K25: 41717
A26: Current Assets | B26: =B24+B25 -> 33325 | C26: =C24+C25 -> 37725 | D26: =D24+D25 -> 42228 | E26: =E24+E25 -> 38302 | F26: =F24+F25 -> 34850 | G26: =G24+G25 -> 35204 | H26: =H24+H25 -> 36457 | I26: =I24+I25 -> 34262 | ... K26: =K24+K25 -> 47071

Sheet Beta Calculation
A1: Date | B1: SunPharma Close | C1: NIFTY Close | D1: Return
A2: 45369 | B2: 1571.25 | C2: 22055.7 | D2: =(C3-C2)/C2 -> -0.010802196
A3: 45370 | B3: 1548.45 | C3: 21817.45 | D3: =(C4-C3)/C3 -> 0.00099232495
A4: 45371 | B4: 1549.35 | C4: 21839.1 | D4: =(C5-C4)/C4 -> 0.0079147034 | F4: Beta | G4: =SLOPE(B2:B248,C2:C248) -> 0.090835513
A5: 45372 | B5: 1565.2 | C5: 22011.95 | D5: =(C6-C5)/C5 -> 0.0038524529
A6: 45373 | B6: 1608.9 | C6: 22096.75 | D6: =(C7-C6)/C6 -> -0.004165771
A7: 45377 | B7: 1598.1 | C7: 22004.7 | D7: =(C8-C7)/C7 -> 0.0054056633
A8: 45378 | B8: 1604.15 | C8: 22123.65 | D8: =(C9-C8)/C8 -> 0.0091870012
A9: 45379 | B9: 1620.55 | C9: 22326.9 | D9: =(C10-C9)/C9 -> 0.0060509968
A10: 45383 | B10: 1629.25 | C10: 22462 | D10: =(C11-C10)/C10 -> -0.00038732081
A11: 45384 | B11: 1622.25 | C11: 22453.3 | D11: =(C12-C11)/C11 -> -0.00083061287
A12: 45385 | B12: 1619.85 | C12: 22434.65 | D12: =(C13-C12)/C12 -> 0.0035659126
A13: 45386 | B13: 1619.35 | C13: 22514.65 | D13: =(C14-C13)/C13 -> -4.2194749e-05
A14: 45387 | B14: 1609 | C14: 22513.7 | D14: =(C15-C14)/C14 -> 0.0067780951
A15: 45390 | B15: 1599.7 | C15: 22666.3 | D15: =(C16-C15)/C15 -> -0.0010389874
A16: 45391 | B16: 1602.55 | C16: 22642.75 | D16: =(C17-C16)/C16 -> 0.0049044396
... A248: 45729 | B248: 1683.45 | C248: 22397.2 | D248: =(C249-C248)/C248 -> -1

Sheet High Growth Phase
C1: Assumptions
A2: Length of High Growth Phase | B2: 2 Years
A3: Growth Rate for revenues, depreciation, EBIT, CapEx | B3: =('Base year & 10 Year data'!K5/'Base year & 10 Year data'!B5)^1/10 -> 0.17704804 | C3: Historical growth rate formula
A4: Cost of debt | B4: =AVERAGE(B32:K32) -> 0.053826843 | C4: Average of historical Cost of Debt
A5: Debt-equity Ratio | B5: 0.04 | C5: Base Year ratio
A6: Risk Free Rate | B6: 0.07 | C6: Assumed
A7: Market Risk Premium | B7: 0.081 | C7: Assumed
A8: Equity Beta | B8: 0.8 | C8: Calculated (based on 1 year historical for 10 years historical)
A9: Corporate Tax Rate | B9: =AVERAGE('Base year & 10 Year data'!B10:K10) -> 0.163 | C9: Average of historical taxes
A11: High Growth Phase | B11: (in crores)
B13: 45717 | C13: 46082
A14: Revenues | B14: =('Base year & 10 Year data'!K5*1.177) -> 57080.969 | C14: =(B14*1.177) -> 67184.301
A15: EBIT | B15: =('Base year & 10 Year data'!K6*1.177) -> 15322.186 | C15: =(B15*1.177) -> 18034.213
A16: EBIT (1-TAX %) | B16: =B15*(1-0.16) -> 12870.636 | C16: =C15*(1-0.16) -> 15148.739
A17: CapEx | B17: =('Base year & 10 Year data'!K7*1.177) -> -2591.754 | C17: =B17*1.177 -> -3050.4945
A18: Depreciation | B18: =('Base year & 10 Year data'!K8*1.177) -> 3009.589 | C18: =B18*1.177 -> 3542.2863
A19: Net Working Capital as % of Revenues | B19: 0.5 | C19: 0.47
A20: Net Working Capital | B20: =B14*0.5 -> 28540.485 | C20: =C14*0.47 -> 31576.621
A21: CapEx - Depreciation' | B21: =B17-B18 -> -5601.343 | C21: =C17-C18 -> -6592.7807
A22: Change in Net Working Capital | B22: =('High Growth Phase'!B20-'Base year & 10 Year data'!K9) -> 3110.4845 | C22: =C20-B20 -> 3036.1367
A24: FCFF | B24: =B16-B21-B22 -> 15361.495 | C24: =C16-C21-C22 -> 18705.383
A27: Cost of Debt Calculation
B29: 42339 | C29: 42705 | D29: 43070 | E29: 43435 | F29: 43800 | G29: 44166 | H29: 44531 | I29: 44896 | J29: 44986 | K29: 45352
A30: Interest | B30: 579 | C30: 523 | D30: 400 | E30: 518 | F30: 555 | G30: 303 | H30: 141 | I30: 127 | J30: 172 | K30: 238
A31: Borrowings | B31: 8996 | C31: 8497 | D31: 9832 | E31: 10385 | F31: 10514 | G31: 8315 | H31: 3869 | I31: 1290 | J31: 6886 | K31: 3274
A32: Cost of Debt | B32: =B30/B31 -> 0.064361939 | C32: =C30/C31 -> 0.061551136 | D32: =D30/D31 -> 0.040683483 | E32: =E30/E31 -> 0.049879634 | F32: =F30/F31 -> 0.052786761 | G32: =G30/G31 -> 0.036440168 | H32: =H30/H31 -> 0.036443525 | I32: =I30/I31 -> 0.098449612 | ... K32: =K30/K31 -> 0.072693952

Sheet Transition Phase
C1: Assumptions
A2: Length of Transition Phase | B2: 2 Years
A3: Growth Rate for revenues, depreciation, EBIT, CapEx | B3: 0.12 | C3: Decreases 2% every year
A4: Cost of debt | B4: 0.07 | C4: Likely to increase due to expansion
A5: Debt-equity Ratio | B5: 0.1 | C5: Company has low leverage
A6: Risk Free Rate | B6: 0.07 | C6: Based on 10 year Government bond yield
A7: Market Risk Premium | B7: 0.07 | C7: Standard
A8: Equity Beta | B8: 0.65 | C8: Estimated
A9: Corporate Tax Rate | B9: 0.25 | C9: Rate fixed
A11: Transition Phase | C11: (in crores)
B13: 46447 | C13: 46813
A14: Revenues | B14: ='High Growth Phase'!C14*1.12 -> 75246.417 | C14: =B14*1.1 -> 82771.058
A15: EBIT | B15: ='High Growth Phase'!C15*1.12 -> 20198.318 | C15: =B15*1.1 -> 22218.15
A16: EBIT (1-TAX %) | B16: =B15*(1-0.25) -> 15148.739 | C16: =C15*(1-0.25) -> 16663.613
A17: CapEx | B17: ='High Growth Phase'!C17*1.12 -> -3416.5538 | C17: =B17*1.1 -> -3758.2092
A18: Depreciation | B18: ='High Growth Phase'!C18*1.12 -> 3967.3606 | C18: =B18*1.11 -> 4403.7703
A19: Net Working Capital as % of Revenues | B19: 0.45 | C19: 0.42
A20: Net Working Capital | B20: =B14*0.45 -> 33860.887 | C20: =C14*0.42 -> 34763.844
A21: CapEx - Depreciation' | B21: =B17-B18 -> -7383.9144 | C21: =C17-C18 -> -8161.9794
A22: Change in Net Working Capital | B22: =B20-'High Growth Phase'!C20 -> 2284.2662 | C22: =C20-B20 -> 902.957
A24: FCFF | B24: =B16-B21-B22 -> 20248.387 | C24: =C16-C21-C22 -> 23922.635

Sheet Stable Phase
C1: Assumptions
A2: Growth Rate for revenues, depreciation, EBIT, CapEx | B2: 0.065 | C2: Geomean of 10 years GDP growth
A3: Cost of debt | B3: 0.06475 | C3: Market interest rate
A4: Debt-equity Ratio | B4: 0.06 | C4: Assumed
A5: Risk Free Rate | B5: 0.08 | C5: Fixed
A6: Market Risk Premium | B6: 0.07 | C6: Assumed
A7: Equity Beta | B7: 0.7 | C7: Standard for Pharma companies
A8: Corporate Tax Rate | B8: 0.25 | C8: Fixed
A11: Stable Growth Phase | B11: (in crores)
B13: 47178
A14: Revenues | B14: ='Transition Phase'!C14*1.065 -> 88151.177
A15: EBIT | B15: ='Transition Phase'!C15*1.065 -> 23662.33
A16: EBIT (1-TAX %) | B16: =B15*(1-0.25) -> 17746.748
A17: CapEx | B17: ='Transition Phase'!C17*1.065 -> -4002.4928
A18: Depreciation | B18: ='Transition Phase'!C18*1.065 -> 4690.0153
A19: Net Working Capital as % of Revenues | B19: 0.38
A20: Net Working Capital | B20: =B14*0.38 -> 33497.447
A21: CapEx - Depreciation' | B21: =B17-B18 -> -8692.5081
A22: Change in Net Working Capital | B22: =B20-'Transition Phase'!C20 -> -1266.3972
A24: FCFF | B24: =B16-B21-B22 -> 27705.653

Sheet Calculated WACC & TV
A2: High Growth Cost of Equity Calculation
A4: Cost of Equity = Risk free rate + Beta*(Market Risk Premium)
A5: Cost of equity | B5: ='High Growth Phase'!B6+'High Growth Phase'!B8*('High Growth Phase'!B7) -> 0.1348
A7: WACC
A8: [(equity/value of firm)*(cost of equity)]+[(value of debt/value of firm)*(cost of debt)*(1-Tax)]
B9: =(24/25*B5)+(1/25*'High Growth Phase'!B4*(1-0.16)) -> 0.13121658
A12: Transition Phase Cost of Equity Calculation
A14: Cost of equity | B14: ='Transition Phase'!B6+'Transition Phase'!B8*('Transition Phase'!B7) -> 0.1155
A16: WACC | B16: =(9/10*B14)+(1/10*'Transition Phase'!B4*(1-'Transition Phase'!B9)) -> 0.1092
A19: Stable Growth Cost of Equity Calculation
A21: Cost of equity | B21: ='Stable Phase'!B5+'Stable Phase'!B7*('Stable Phase'!B6) -> 0.129
A23: WACC | B23: =47/50*B21+3/50*'Stable Phase'!B3*(1-'Stable Phase'!B8) -> 0.12417375
A26: Present Value of FCFF
A28: Terminal Value
A29: [FCFF*(1+ Growth rate)]/[(WACC-Growth rate)] | B29: =('Stable Phase'!B24*(1+6.5%)/'Calculated WACC & TV'!B23-6.5%) -> 237622.78
A31: Present Value of Terminal Value | B31: =PV(0.65,5, 0, -237622.78, 0) -> 19429.801

Sheet Value of Firm
A1: Year | B1: FCFF (₹ crores) | C1: Discounted Value (₹ crores)
A2: 2025 | B2: 15361.49 | C2: =15361.49/(1.1312)^1 -> 13579.818
A3: 2026 | B3: 18705.38 | C3: =B3/(1.1312)^2 -> 14617.993
A4: 2027 | B4: 20248.39 | C4: =B4/(1.1092)*(1.1312)^2 -> 23359.279
A5: 2028 | B5: 23922.64 | C5: =B5/(1.1092)^2*(1.1312)^2 -> 24881.02
A6: 2029 | B6: 27705.65 | C6: =B6/(1.1242)*(1.1312)^2 -> 31535.778
A8: Value of Firm
B9: =SUM(C2:C6,'Calculated WACC & TV'!B31) -> 127403.69 | C9: crores
